{"name":"bash","postlist":[{"title":"Linux 常用其他命令","slug":"linux 项目部署/[Linux]  常用命令（汇总）","date":"2021-01-18T15:09:16.994Z","updated":"2021-01-18T15:10:17.514Z","comments":true,"path":"api/articles/linux 项目部署/[Linux]  常用命令（汇总）.json","excerpt":null,"keywords":null,"cover":"https://images2018.cnblogs.com/blog/1132884/201807/1132884-20180723170115394-866303539.png","content":null,"raw":null,"categories":[{"name":"linux","path":"api/categories/linux.json"}],"tags":[{"name":"linux","path":"api/tags/linux.json"},{"name":"bash","path":"api/tags/bash.json"}]}]}